Workbook

Sheet Resumen
A1: Administración Departamentos Chichén Itzá
A2: Celdas amarillas = para llenar. Lo demás se calcula solo.
A4: Administrador(a)
A5: Periodo
A6: Nombre Mes 1 | B6: Mes 1
A7: Nombre Mes 2 | B7: Mes 2
A8: Nombre Mes 3 | B8: Mes 3
A9: Cuota mensual por depa | B9: 1000
A10: Saldo inicial (recibido de la administración anterior) | C10: Si la administración anterior entregó saldo negativo, escríbelo con signo menos.
A12: Cobrado (mantenimiento + extraordinarias) | B12: =Ingresos!G15 -> 0
A13: Por cobrar | B13: =B9*3*COUNTA(Ingresos!A6:A14)-SUM(Ingresos!C15:E15) -> 27000
A14: Pagos al conserje | B14: =Conserje!C31 -> 0
A15: Otros gastos | B15: ='Otros Gastos'!C36 -> 0
A16: Total gastos | B16: =B14+B15 -> 0
A17: Saldo final | B17: =B10+B12-B16 -> 0
A19: Cómo usar
A20: 1. Llena las celdas amarillas de esta hoja (periodo, nombres de los meses, cuota y saldo inicial).
A21: 2. En 'Ingresos', escribe el propietario de cada depa y el monto que pagó en cada mes. Déjalo vacío si no ha pagado.
A22: 3. En 'Conserje' y 'Otros Gastos', agrega una fila por pago con concepto, fecha (dd/mm/aaaa) y monto.
A23: 4. La fila gris de 'Ejemplo' en cada hoja no suma. Puedes borrarla o dejarla de guía.

Sheet Ingresos
A1: Ingresos por departamento
A2: Escribe el monto pagado en cada mes (vacío = pendiente). La columna Extraordinaria es para adelantos o aportaciones fuera de la cuota.
A3: Depa | B3: Propietario | C3: =Resumen!B6 -> Mes 1 | D3: =Resumen!B7 -> Mes 2 | E3: =Resumen!B8 -> Mes 3 | F3: Extraordinaria | G3: Total pagado | H3: Nota
A4: Ejemplo | B4: Nombre | C4: 1000 | D4: 1000 | F4: 1000 | G4: =SUM(C4:F4) -> 3000 | H4: Adelanto para pago del conserje
A5: (la fila de ejemplo no suma)
A6: Depa 1 | G6: =SUM(C6:F6) -> 0
A7: Depa 2 | G7: =SUM(C7:F7) -> 0
A8: Depa 3 | G8: =SUM(C8:F8) -> 0
A9: Depa 4 | G9: =SUM(C9:F9) -> 0
A10: Depa 5 | G10: =SUM(C10:F10) -> 0
A11: Depa 6 | G11: =SUM(C11:F11) -> 0
A12: Depa 7 | G12: =SUM(C12:F12) -> 0
A13: Depa 8 | G13: =SUM(C13:F13) -> 0
A14: Depa 9 | G14: =SUM(C14:F14) -> 0
A15: TOTAL | C15: =SUM(C6:C14) -> 0 | D15: =SUM(D6:D14) -> 0 | E15: =SUM(E6:E14) -> 0 | F15: =SUM(F6:F14) -> 0 | G15: =SUM(G6:G14) -> 0

Sheet Conserje
A1: Pagos al conserje
A3: Concepto | B3: Fecha | C3: Monto
A4: Pago semanal conserje | B4: dd/mm/aaaa | C4: 1400
A5: (la fila de ejemplo no suma)
A31: TOTAL | C31: =SUM(C6:C30) -> 0

Sheet Otros Gastos
A1: Otros gastos
A3: Concepto | B3: Fecha | C3: Monto
A4: Recibo luz CFE | B4: dd/mm/aaaa | C4: 1400
A5: (la fila de ejemplo no suma)
A36: TOTAL | C36: =SUM(C6:C35) -> 0
